itk_binarythinning3d-5.0b1.dist-info/RECORD
itk_binarythinning3d-5.0b1.dist-info/METADATA
itk_binarythinning3d-5.0b1.dist-info/WHEEL
itk_binarythinning3d-5.0b1.dist-info/top_level.txt
itk/BinaryThinning3DPython.py
itk/itkBinaryThinningImageFilter3DPython.py
itk/_BinaryThinning3DPython.so
itk/Configuration/BinaryThinning3DConfig.py
